{
    "frames": {
        "205058_effect.png": {
            "frame": {
                "h": 99,
                "w": 71,
                "x": 2,
                "y": 70
            },
            "rotated": false,
            "sourceSize": {
                "h": 120,
                "w": 80
            },
            "spriteSourceSize": {
                "h": 99,
                "w": 71,
                "x": 1,
                "y": 0
            },
            "trimmed": true
        },
        "205058_in.png": {
            "frame": {
                "h": 65,
                "w": 38,
                "x": 82,
                "y": 2
            },
            "rotated": false,
            "sourceSize": {
                "h": 120,
                "w": 80
            },
            "spriteSourceSize": {
                "h": 65,
                "w": 38,
                "x": 20,
                "y": 38
            },
            "trimmed": true
        },
        "205058_top.png": {
            "frame": {
                "h": 66,
                "w": 64,
                "x": 2,
                "y": 171
            },
            "rotated": false,
            "sourceSize": {
                "h": 120,
                "w": 80
            },
            "spriteSourceSize": {
                "h": 66,
                "w": 64,
                "x": 4,
                "y": 1
            },
            "trimmed": true
        },
        "205058_under.png": {
            "frame": {
                "h": 66,
                "w": 78,
                "x": 2,
                "y": 2
            },
            "rotated": false,
            "sourceSize": {
                "h": 120,
                "w": 80
            },
            "spriteSourceSize": {
                "h": 66,
                "w": 78,
                "x": 2,
                "y": 49
            },
            "trimmed": true
        }
    },
    "meta": {
        "app": "ImagePacker",
        "format": "RGBA8888",
        "image": "205058.png",
        "size": {
            "h": 256,
            "w": 128
        },
        "version": "20130624_0"
    }
}