{
    "action": [
        {
            "actionName": "action_next",
            "frame": 600
        }
    ],
    "fps": 60,
    "meta": {
        "app": "AnimationBuilder",
        "app_ver": "20141031_0",
        "core_ver": "1.0",
        "created_date": "水 5月 20 10:33:29 2015",
        "date": "木 5月 21 18:04:26 2015",
        "runtime_type": "cocos2d-x",
        "runtime_ver": "2.1.4",
        "ver": "0.05"
    },
    "screenSize": {
        "h": 480,
        "w": 320
    },
    "tag": {
        "hit": [
            400,
            630,
            0
        ],
        "play": [
            16,
            630,
            0
        ]
    },
    "tree": [
        {
            "attrs": {
                "alpha": 1,
                "anchor": [
                    0,
                    0
                ],
                "color": [
                    1,
                    1,
                    1
                ],
                "frame": [
                    160,
                    240,
                    0,
                    0
                ],
                "rotation": [
                    0,
                    0,
                    0
                ],
                "scale": [
                    1,
                    1
                ],
                "visible": false
            },
            "children": [
                {
                    "attrs": {
                        "alpha": 1,
                        "anchor": [
                            0.5,
                            0.5
                        ],
                        "color": [
                            1,
                            1,
                            1
                        ],
                        "frame": [
                            0,
                            0,
                            64,
                            64
                        ],
                        "rotation": [
                            0,
                            0,
                            0
                        ],
                        "scale": [
                            1,
                            1
                        ],
                        "visible": true
                    },
                    "children": [
                        {
                            "attrs": {
                                "alpha": 1,
                                "color": [
                                    1,
                                    1,
                                    1
                                ],
                                "frame": [
                                    0,
                                    0,
                                    64,
                                    64
                                ],
                                "particle": {
                                    "attractor": "",
                                    "file": "/Content/lang/ww/compile/en/ab/ability/70743/pb_heist_circle.json",
                                    "frame": 400
                                },
                                "rotation": [
                                    0,
                                    0,
                                    0
                                ],
                                "scale": [
                                    1,
                                    1
                                ],
                                "visible": true
                            },
                            "name": "heist",
                            "type": "particle"
                        },
                        {
                            "attrs": {
                                "alpha": 0,
                                "anchor": [
                                    0.5,
                                    0.5
                                ],
                                "anime": {
                                    "alpha": [
                                        {
                                            "point": [
                                                430,
                                                0,
                                                432,
                                                1
                                            ],
                                            "type": "liner"
                                        },
                                        {
                                            "point": [
                                                432,
                                                1,
                                                499,
                                                1
                                            ],
                                            "type": "liner"
                                        },
                                        {
                                            "point": [
                                                499,
                                                1,
                                                509,
                                                0
                                            ],
                                            "type": "liner"
                                        }
                                    ],
                                    "rotZ": [
                                        {
                                            "point": [
                                                430,
                                                0,
                                                502.276336669922,
                                                16.8318119049072,
                                                509,
                                                65.1428680419922,
                                                509,
                                                480
                                            ],
                                            "type": "spline"
                                        }
                                    ]
                                },
                                "blend": "add",
                                "color": [
                                    1,
                                    0.474509803921569,
                                    0.125490196078431
                                ],
                                "filtering": false,
                                "frame": [
                                    0,
                                    0,
                                    64,
                                    64
                                ],
                                "image": {
                                    "file": "/Content/lang/ww/compile/en/ab/effect_image/orso_clock_parts_001.json",
                                    "packerid": "64_clock_201_wb.png",
                                    "url": "/Content/lang/ww/compile/en/ab/effect_image/orso_clock_parts_001.png",
                                    "uvs": [
                                        0,
                                        0.5,
                                        0.5,
                                        0.5
                                    ]
                                },
                                "rotation": [
                                    0,
                                    0,
                                    0
                                ],
                                "scale": [
                                    1,
                                    1
                                ],
                                "visible": true
                            },
                            "name": "clock_shortHand_3",
                            "type": "image"
                        },
                        {
                            "attrs": {
                                "alpha": 0,
                                "anchor": [
                                    0.5,
                                    0.5
                                ],
                                "anime": {
                                    "alpha": [
                                        {
                                            "point": [
                                                430,
                                                0,
                                                432,
                                                1
                                            ],
                                            "type": "liner"
                                        },
                                        {
                                            "point": [
                                                432,
                                                1,
                                                499,
                                                1
                                            ],
                                            "type": "liner"
                                        },
                                        {
                                            "point": [
                                                499,
                                                1,
                                                509,
                                                0
                                            ],
                                            "type": "liner"
                                        }
                                    ],
                                    "rotZ": [
                                        {
                                            "point": [
                                                430,
                                                90,
                                                507.411773681641,
                                                97.6175231933594,
                                                509,
                                                219.428588867188,
                                                509,
                                                960
                                            ],
                                            "type": "spline"
                                        }
                                    ]
                                },
                                "blend": "add",
                                "color": [
                                    1,
                                    0.474509803921569,
                                    0.125490196078431
                                ],
                                "filtering": false,
                                "frame": [
                                    0,
                                    0,
                                    64,
                                    64
                                ],
                                "image": {
                                    "file": "/Content/lang/ww/compile/en/ab/effect_image/orso_clock_parts_001.json",
                                    "packerid": "64_clock_301_wb.png",
                                    "url": "/Content/lang/ww/compile/en/ab/effect_image/orso_clock_parts_001.png",
                                    "uvs": [
                                        0,
                                        0,
                                        0.5,
                                        0.5
                                    ]
                                },
                                "rotation": [
                                    0,
                                    0,
                                    90
                                ],
                                "scale": [
                                    1,
                                    1
                                ],
                                "visible": true
                            },
                            "name": "clock_LongHand_3",
                            "type": "image"
                        },
                        {
                            "attrs": {
                                "alpha": 1,
                                "color": [
                                    1,
                                    1,
                                    1
                                ],
                                "frame": [
                                    0,
                                    0,
                                    64,
                                    64
                                ],
                                "particle": {
                                    "attractor": "",
                                    "file": "/Content/lang/ww/compile/en/ab/ability/70743/pb_heist.json",
                                    "frame": 407
                                },
                                "rotation": [
                                    0,
                                    0,
                                    0
                                ],
                                "scale": [
                                    1,
                                    1
                                ],
                                "visible": true
                            },
                            "name": "heist_1",
                            "type": "particle"
                        },
                        {
                            "attrs": {
                                "alpha": 1,
                                "color": [
                                    1,
                                    1,
                                    1
                                ],
                                "frame": [
                                    0,
                                    0,
                                    64,
                                    64
                                ],
                                "particle": {
                                    "attractor": "",
                                    "file": "/Content/lang/ww/compile/en/ab/ability/70743/pb_hit_cure.json",
                                    "frame": 490
                                },
                                "rotation": [
                                    0,
                                    0,
                                    0
                                ],
                                "scale": [
                                    1,
                                    1
                                ],
                                "visible": true
                            },
                            "name": "ptcl_cure",
                            "type": "particle"
                        }
                    ],
                    "isCreate": true,
                    "name": "ability_hit_nul",
                    "type": "null"
                }
            ],
            "isCreate": true,
            "name": "visible_nul",
            "type": "null"
        }
    ]
}