{
    "frames": {
        "base_chant_1.png": {
            "frame": {
                "h": 24,
                "w": 16,
                "x": 19,
                "y": 26
            },
            "rotated": false,
            "sourceSize": {
                "h": 32,
                "w": 32
            },
            "spriteSourceSize": {
                "h": 24,
                "w": 16,
                "x": 8,
                "y": 4
            },
            "trimmed": true
        },
        "base_chant_2.png": {
            "frame": {
                "h": 24,
                "w": 16,
                "x": 19,
                "y": 1
            },
            "rotated": false,
            "sourceSize": {
                "h": 32,
                "w": 32
            },
            "spriteSourceSize": {
                "h": 24,
                "w": 16,
                "x": 8,
                "y": 4
            },
            "trimmed": true
        },
        "base_damage.png": {
            "frame": {
                "h": 24,
                "w": 16,
                "x": 1,
                "y": 201
            },
            "rotated": false,
            "sourceSize": {
                "h": 32,
                "w": 32
            },
            "spriteSourceSize": {
                "h": 24,
                "w": 16,
                "x": 8,
                "y": 4
            },
            "trimmed": true
        },
        "base_damage_thunder.png": {
            "frame": {
                "h": 24,
                "w": 16,
                "x": 18,
                "y": 51
            },
            "rotated": false,
            "sourceSize": {
                "h": 32,
                "w": 32
            },
            "spriteSourceSize": {
                "h": 24,
                "w": 16,
                "x": 8,
                "y": 4
            },
            "trimmed": true
        },
        "base_damage_white.png": {
            "frame": {
                "h": 24,
                "w": 16,
                "x": 1,
                "y": 226
            },
            "rotated": false,
            "sourceSize": {
                "h": 32,
                "w": 32
            },
            "spriteSourceSize": {
                "h": 24,
                "w": 16,
                "x": 8,
                "y": 4
            },
            "trimmed": true
        },
        "base_dead.png": {
            "frame": {
                "h": 16,
                "w": 24,
                "x": 92,
                "y": 69
            },
            "rotated": false,
            "sourceSize": {
                "h": 32,
                "w": 32
            },
            "spriteSourceSize": {
                "h": 16,
                "w": 24,
                "x": 4,
                "y": 12
            },
            "trimmed": true
        },
        "base_dead_white.png": {
            "frame": {
                "h": 16,
                "w": 24,
                "x": 67,
                "y": 70
            },
            "rotated": false,
            "sourceSize": {
                "h": 32,
                "w": 32
            },
            "spriteSourceSize": {
                "h": 16,
                "w": 24,
                "x": 4,
                "y": 12
            },
            "trimmed": true
        },
        "base_fatal.png": {
            "frame": {
                "h": 20,
                "w": 16,
                "x": 50,
                "y": 124
            },
            "rotated": false,
            "sourceSize": {
                "h": 32,
                "w": 32
            },
            "spriteSourceSize": {
                "h": 20,
                "w": 16,
                "x": 9,
                "y": 8
            },
            "trimmed": true
        },
        "base_fatal_white.png": {
            "frame": {
                "h": 20,
                "w": 16,
                "x": 70,
                "y": 22
            },
            "rotated": false,
            "sourceSize": {
                "h": 32,
                "w": 32
            },
            "spriteSourceSize": {
                "h": 20,
                "w": 16,
                "x": 9,
                "y": 8
            },
            "trimmed": true
        },
        "base_hands_up.png": {
            "frame": {
                "h": 24,
                "w": 14,
                "x": 18,
                "y": 176
            },
            "rotated": false,
            "sourceSize": {
                "h": 32,
                "w": 32
            },
            "spriteSourceSize": {
                "h": 24,
                "w": 14,
                "x": 10,
                "y": 4
            },
            "trimmed": true
        },
        "base_idle.png": {
            "frame": {
                "h": 24,
                "w": 15,
                "x": 18,
                "y": 151
            },
            "rotated": false,
            "sourceSize": {
                "h": 32,
                "w": 32
            },
            "spriteSourceSize": {
                "h": 24,
                "w": 15,
                "x": 9,
                "y": 4
            },
            "trimmed": true
        },
        "base_idle_cut.png": {
            "frame": {
                "h": 16,
                "w": 14,
                "x": 96,
                "y": 39
            },
            "rotated": false,
            "sourceSize": {
                "h": 32,
                "w": 32
            },
            "spriteSourceSize": {
                "h": 16,
                "w": 14,
                "x": 9,
                "y": 16
            },
            "trimmed": true
        },
        "base_idle_white.png": {
            "frame": {
                "h": 24,
                "w": 15,
                "x": 18,
                "y": 101
            },
            "rotated": false,
            "sourceSize": {
                "h": 32,
                "w": 32
            },
            "spriteSourceSize": {
                "h": 24,
                "w": 15,
                "x": 9,
                "y": 4
            },
            "trimmed": true
        },
        "base_left_arm_1.png": {
            "frame": {
                "h": 23,
                "w": 15,
                "x": 51,
                "y": 75
            },
            "rotated": false,
            "sourceSize": {
                "h": 32,
                "w": 32
            },
            "spriteSourceSize": {
                "h": 23,
                "w": 15,
                "x": 9,
                "y": 5
            },
            "trimmed": true
        },
        "base_left_arm_2.png": {
            "frame": {
                "h": 23,
                "w": 15,
                "x": 50,
                "y": 100
            },
            "rotated": false,
            "sourceSize": {
                "h": 32,
                "w": 32
            },
            "spriteSourceSize": {
                "h": 23,
                "w": 15,
                "x": 9,
                "y": 5
            },
            "trimmed": true
        },
        "base_left_arm_3.png": {
            "frame": {
                "h": 11,
                "w": 8,
                "x": 89,
                "y": 87
            },
            "rotated": false,
            "sourceSize": {
                "h": 32,
                "w": 32
            },
            "spriteSourceSize": {
                "h": 11,
                "w": 8,
                "x": 14,
                "y": 7
            },
            "trimmed": true
        },
        "base_left_arm_4.png": {
            "frame": {
                "h": 6,
                "w": 8,
                "x": 27,
                "y": 249
            },
            "rotated": false,
            "sourceSize": {
                "h": 32,
                "w": 32
            },
            "spriteSourceSize": {
                "h": 6,
                "w": 8,
                "x": 11,
                "y": 17
            },
            "trimmed": true
        },
        "base_ready.png": {
            "frame": {
                "h": 23,
                "w": 16,
                "x": 36,
                "y": 25
            },
            "rotated": false,
            "sourceSize": {
                "h": 32,
                "w": 32
            },
            "spriteSourceSize": {
                "h": 23,
                "w": 16,
                "x": 8,
                "y": 5
            },
            "trimmed": true
        },
        "base_right_arm_1.png": {
            "frame": {
                "h": 23,
                "w": 15,
                "x": 34,
                "y": 148
            },
            "rotated": false,
            "sourceSize": {
                "h": 32,
                "w": 32
            },
            "spriteSourceSize": {
                "h": 23,
                "w": 15,
                "x": 9,
                "y": 5
            },
            "trimmed": true
        },
        "base_right_arm_2.png": {
            "frame": {
                "h": 23,
                "w": 15,
                "x": 34,
                "y": 124
            },
            "rotated": false,
            "sourceSize": {
                "h": 32,
                "w": 32
            },
            "spriteSourceSize": {
                "h": 23,
                "w": 15,
                "x": 9,
                "y": 5
            },
            "trimmed": true
        },
        "base_special_attack.png": {
            "frame": {
                "h": 23,
                "w": 16,
                "x": 35,
                "y": 51
            },
            "rotated": false,
            "sourceSize": {
                "h": 32,
                "w": 32
            },
            "spriteSourceSize": {
                "h": 23,
                "w": 16,
                "x": 8,
                "y": 5
            },
            "trimmed": true
        },
        "base_special_ready.png": {
            "frame": {
                "h": 23,
                "w": 16,
                "x": 34,
                "y": 76
            },
            "rotated": false,
            "sourceSize": {
                "h": 32,
                "w": 32
            },
            "spriteSourceSize": {
                "h": 23,
                "w": 16,
                "x": 8,
                "y": 5
            },
            "trimmed": true
        },
        "base_walk.png": {
            "frame": {
                "h": 23,
                "w": 15,
                "x": 34,
                "y": 100
            },
            "rotated": false,
            "sourceSize": {
                "h": 32,
                "w": 32
            },
            "spriteSourceSize": {
                "h": 23,
                "w": 15,
                "x": 9,
                "y": 5
            },
            "trimmed": true
        },
        "frog_attack.png": {
            "frame": {
                "h": 14,
                "w": 16,
                "x": 119,
                "y": 1
            },
            "rotated": false,
            "sourceSize": {
                "h": 32,
                "w": 32
            },
            "spriteSourceSize": {
                "h": 14,
                "w": 16,
                "x": 8,
                "y": 10
            },
            "trimmed": true
        },
        "frog_damage.png": {
            "frame": {
                "h": 16,
                "w": 14,
                "x": 89,
                "y": 1
            },
            "rotated": false,
            "sourceSize": {
                "h": 32,
                "w": 32
            },
            "spriteSourceSize": {
                "h": 16,
                "w": 14,
                "x": 9,
                "y": 8
            },
            "trimmed": true
        },
        "frog_damage_thunder.png": {
            "frame": {
                "h": 16,
                "w": 14,
                "x": 104,
                "y": 1
            },
            "rotated": false,
            "sourceSize": {
                "h": 32,
                "w": 32
            },
            "spriteSourceSize": {
                "h": 16,
                "w": 14,
                "x": 9,
                "y": 8
            },
            "trimmed": true
        },
        "frog_damage_white.png": {
            "frame": {
                "h": 16,
                "w": 14,
                "x": 103,
                "y": 18
            },
            "rotated": false,
            "sourceSize": {
                "h": 32,
                "w": 32
            },
            "spriteSourceSize": {
                "h": 16,
                "w": 14,
                "x": 9,
                "y": 8
            },
            "trimmed": true
        },
        "frog_dead.png": {
            "frame": {
                "h": 8,
                "w": 16,
                "x": 88,
                "y": 60
            },
            "rotated": false,
            "sourceSize": {
                "h": 32,
                "w": 32
            },
            "spriteSourceSize": {
                "h": 8,
                "w": 16,
                "x": 8,
                "y": 16
            },
            "trimmed": true
        },
        "frog_dead_white.png": {
            "frame": {
                "h": 8,
                "w": 16,
                "x": 71,
                "y": 60
            },
            "rotated": false,
            "sourceSize": {
                "h": 32,
                "w": 32
            },
            "spriteSourceSize": {
                "h": 8,
                "w": 16,
                "x": 8,
                "y": 16
            },
            "trimmed": true
        },
        "frog_fatal.png": {
            "frame": {
                "h": 10,
                "w": 15,
                "x": 67,
                "y": 127
            },
            "rotated": false,
            "sourceSize": {
                "h": 32,
                "w": 32
            },
            "spriteSourceSize": {
                "h": 10,
                "w": 15,
                "x": 9,
                "y": 14
            },
            "trimmed": true
        },
        "frog_fatal_white.png": {
            "frame": {
                "h": 10,
                "w": 15,
                "x": 67,
                "y": 116
            },
            "rotated": false,
            "sourceSize": {
                "h": 32,
                "w": 32
            },
            "spriteSourceSize": {
                "h": 10,
                "w": 15,
                "x": 9,
                "y": 14
            },
            "trimmed": true
        },
        "frog_idle.png": {
            "frame": {
                "h": 13,
                "w": 15,
                "x": 50,
                "y": 159
            },
            "rotated": false,
            "sourceSize": {
                "h": 32,
                "w": 32
            },
            "spriteSourceSize": {
                "h": 13,
                "w": 15,
                "x": 9,
                "y": 11
            },
            "trimmed": true
        },
        "frog_idle_white.png": {
            "frame": {
                "h": 13,
                "w": 15,
                "x": 50,
                "y": 145
            },
            "rotated": false,
            "sourceSize": {
                "h": 32,
                "w": 32
            },
            "spriteSourceSize": {
                "h": 13,
                "w": 15,
                "x": 9,
                "y": 11
            },
            "trimmed": true
        },
        "frog_jump.png": {
            "frame": {
                "h": 15,
                "w": 16,
                "x": 111,
                "y": 35
            },
            "rotated": false,
            "sourceSize": {
                "h": 32,
                "w": 32
            },
            "spriteSourceSize": {
                "h": 15,
                "w": 16,
                "x": 8,
                "y": 9
            },
            "trimmed": true
        },
        "frog_paralysis.png": {
            "frame": {
                "h": 16,
                "w": 15,
                "x": 87,
                "y": 22
            },
            "rotated": false,
            "sourceSize": {
                "h": 32,
                "w": 32
            },
            "spriteSourceSize": {
                "h": 16,
                "w": 15,
                "x": 9,
                "y": 8
            },
            "trimmed": true
        },
        "frog_ready.png": {
            "frame": {
                "h": 15,
                "w": 14,
                "x": 118,
                "y": 18
            },
            "rotated": false,
            "sourceSize": {
                "h": 32,
                "w": 32
            },
            "spriteSourceSize": {
                "h": 15,
                "w": 14,
                "x": 9,
                "y": 9
            },
            "trimmed": true
        },
        "glass_chant_1.png": {
            "frame": {
                "h": 24,
                "w": 16,
                "x": 1,
                "y": 176
            },
            "rotated": false,
            "sourceSize": {
                "h": 32,
                "w": 32
            },
            "spriteSourceSize": {
                "h": 24,
                "w": 16,
                "x": 8,
                "y": 4
            },
            "trimmed": true
        },
        "glass_chant_2.png": {
            "frame": {
                "h": 24,
                "w": 16,
                "x": 1,
                "y": 151
            },
            "rotated": false,
            "sourceSize": {
                "h": 32,
                "w": 32
            },
            "spriteSourceSize": {
                "h": 24,
                "w": 16,
                "x": 8,
                "y": 4
            },
            "trimmed": true
        },
        "glass_damage.png": {
            "frame": {
                "h": 24,
                "w": 16,
                "x": 1,
                "y": 76
            },
            "rotated": false,
            "sourceSize": {
                "h": 32,
                "w": 32
            },
            "spriteSourceSize": {
                "h": 24,
                "w": 16,
                "x": 8,
                "y": 4
            },
            "trimmed": true
        },
        "glass_damage_thunder.png": {
            "frame": {
                "h": 24,
                "w": 16,
                "x": 1,
                "y": 126
            },
            "rotated": false,
            "sourceSize": {
                "h": 32,
                "w": 32
            },
            "spriteSourceSize": {
                "h": 24,
                "w": 16,
                "x": 8,
                "y": 4
            },
            "trimmed": true
        },
        "glass_damage_white.png": {
            "frame": {
                "h": 24,
                "w": 16,
                "x": 1,
                "y": 101
            },
            "rotated": false,
            "sourceSize": {
                "h": 32,
                "w": 32
            },
            "spriteSourceSize": {
                "h": 24,
                "w": 16,
                "x": 8,
                "y": 4
            },
            "trimmed": true
        },
        "glass_dead.png": {
            "frame": {
                "h": 16,
                "w": 24,
                "x": 71,
                "y": 43
            },
            "rotated": false,
            "sourceSize": {
                "h": 32,
                "w": 32
            },
            "spriteSourceSize": {
                "h": 16,
                "w": 24,
                "x": 4,
                "y": 12
            },
            "trimmed": true
        },
        "glass_dead_white.png": {
            "frame": {
                "h": 16,
                "w": 24,
                "x": 66,
                "y": 99
            },
            "rotated": false,
            "sourceSize": {
                "h": 32,
                "w": 32
            },
            "spriteSourceSize": {
                "h": 16,
                "w": 24,
                "x": 4,
                "y": 12
            },
            "trimmed": true
        },
        "glass_fatal.png": {
            "frame": {
                "h": 20,
                "w": 18,
                "x": 53,
                "y": 1
            },
            "rotated": false,
            "sourceSize": {
                "h": 32,
                "w": 32
            },
            "spriteSourceSize": {
                "h": 20,
                "w": 18,
                "x": 7,
                "y": 8
            },
            "trimmed": true
        },
        "glass_fatal_white.png": {
            "frame": {
                "h": 20,
                "w": 18,
                "x": 52,
                "y": 49
            },
            "rotated": false,
            "sourceSize": {
                "h": 32,
                "w": 32
            },
            "spriteSourceSize": {
                "h": 20,
                "w": 18,
                "x": 7,
                "y": 8
            },
            "trimmed": true
        },
        "glass_hands_up.png": {
            "frame": {
                "h": 24,
                "w": 16,
                "x": 1,
                "y": 51
            },
            "rotated": false,
            "sourceSize": {
                "h": 32,
                "w": 32
            },
            "spriteSourceSize": {
                "h": 24,
                "w": 16,
                "x": 8,
                "y": 4
            },
            "trimmed": true
        },
        "glass_idle.png": {
            "frame": {
                "h": 24,
                "w": 17,
                "x": 1,
                "y": 26
            },
            "rotated": false,
            "sourceSize": {
                "h": 32,
                "w": 32
            },
            "spriteSourceSize": {
                "h": 24,
                "w": 17,
                "x": 7,
                "y": 4
            },
            "trimmed": true
        },
        "glass_idle_white.png": {
            "frame": {
                "h": 24,
                "w": 17,
                "x": 1,
                "y": 1
            },
            "rotated": false,
            "sourceSize": {
                "h": 32,
                "w": 32
            },
            "spriteSourceSize": {
                "h": 24,
                "w": 17,
                "x": 7,
                "y": 4
            },
            "trimmed": true
        },
        "glass_left_arm_1.png": {
            "frame": {
                "h": 23,
                "w": 17,
                "x": 36,
                "y": 224
            },
            "rotated": false,
            "sourceSize": {
                "h": 32,
                "w": 32
            },
            "spriteSourceSize": {
                "h": 23,
                "w": 17,
                "x": 7,
                "y": 5
            },
            "trimmed": true
        },
        "glass_left_arm_2.png": {
            "frame": {
                "h": 23,
                "w": 17,
                "x": 36,
                "y": 200
            },
            "rotated": false,
            "sourceSize": {
                "h": 32,
                "w": 32
            },
            "spriteSourceSize": {
                "h": 23,
                "w": 17,
                "x": 7,
                "y": 5
            },
            "trimmed": true
        },
        "glass_left_arm_3.png": {
            "frame": {
                "h": 11,
                "w": 8,
                "x": 80,
                "y": 87
            },
            "rotated": false,
            "sourceSize": {
                "h": 32,
                "w": 32
            },
            "spriteSourceSize": {
                "h": 11,
                "w": 8,
                "x": 14,
                "y": 7
            },
            "trimmed": true
        },
        "glass_left_arm_4.png": {
            "frame": {
                "h": 6,
                "w": 8,
                "x": 18,
                "y": 249
            },
            "rotated": false,
            "sourceSize": {
                "h": 32,
                "w": 32
            },
            "spriteSourceSize": {
                "h": 6,
                "w": 8,
                "x": 11,
                "y": 17
            },
            "trimmed": true
        },
        "glass_ready.png": {
            "frame": {
                "h": 23,
                "w": 16,
                "x": 36,
                "y": 1
            },
            "rotated": false,
            "sourceSize": {
                "h": 32,
                "w": 32
            },
            "spriteSourceSize": {
                "h": 23,
                "w": 16,
                "x": 8,
                "y": 5
            },
            "trimmed": true
        },
        "glass_right_arm_1.png": {
            "frame": {
                "h": 23,
                "w": 17,
                "x": 18,
                "y": 225
            },
            "rotated": false,
            "sourceSize": {
                "h": 32,
                "w": 32
            },
            "spriteSourceSize": {
                "h": 23,
                "w": 17,
                "x": 7,
                "y": 5
            },
            "trimmed": true
        },
        "glass_right_arm_2.png": {
            "frame": {
                "h": 23,
                "w": 17,
                "x": 33,
                "y": 176
            },
            "rotated": false,
            "sourceSize": {
                "h": 32,
                "w": 32
            },
            "spriteSourceSize": {
                "h": 23,
                "w": 17,
                "x": 7,
                "y": 5
            },
            "trimmed": true
        },
        "glass_walk.png": {
            "frame": {
                "h": 23,
                "w": 17,
                "x": 18,
                "y": 201
            },
            "rotated": false,
            "sourceSize": {
                "h": 32,
                "w": 32
            },
            "spriteSourceSize": {
                "h": 23,
                "w": 17,
                "x": 7,
                "y": 5
            },
            "trimmed": true
        },
        "mini_attack.png": {
            "frame": {
                "h": 12,
                "w": 12,
                "x": 54,
                "y": 199
            },
            "rotated": false,
            "sourceSize": {
                "h": 32,
                "w": 32
            },
            "spriteSourceSize": {
                "h": 12,
                "w": 12,
                "x": 11,
                "y": 12
            },
            "trimmed": true
        },
        "mini_damage.png": {
            "frame": {
                "h": 12,
                "w": 12,
                "x": 105,
                "y": 56
            },
            "rotated": false,
            "sourceSize": {
                "h": 32,
                "w": 32
            },
            "spriteSourceSize": {
                "h": 12,
                "w": 12,
                "x": 12,
                "y": 12
            },
            "trimmed": true
        },
        "mini_damage_thunder.png": {
            "frame": {
                "h": 12,
                "w": 12,
                "x": 51,
                "y": 186
            },
            "rotated": false,
            "sourceSize": {
                "h": 32,
                "w": 32
            },
            "spriteSourceSize": {
                "h": 12,
                "w": 12,
                "x": 12,
                "y": 12
            },
            "trimmed": true
        },
        "mini_damage_white.png": {
            "frame": {
                "h": 12,
                "w": 12,
                "x": 51,
                "y": 173
            },
            "rotated": false,
            "sourceSize": {
                "h": 32,
                "w": 32
            },
            "spriteSourceSize": {
                "h": 12,
                "w": 12,
                "x": 12,
                "y": 12
            },
            "trimmed": true
        },
        "mini_dead.png": {
            "frame": {
                "h": 7,
                "w": 16,
                "x": 53,
                "y": 248
            },
            "rotated": false,
            "sourceSize": {
                "h": 32,
                "w": 32
            },
            "spriteSourceSize": {
                "h": 7,
                "w": 16,
                "x": 8,
                "y": 17
            },
            "trimmed": true
        },
        "mini_dead_white.png": {
            "frame": {
                "h": 7,
                "w": 16,
                "x": 36,
                "y": 248
            },
            "rotated": false,
            "sourceSize": {
                "h": 32,
                "w": 32
            },
            "spriteSourceSize": {
                "h": 7,
                "w": 16,
                "x": 8,
                "y": 17
            },
            "trimmed": true
        },
        "mini_fatal.png": {
            "frame": {
                "h": 10,
                "w": 10,
                "x": 54,
                "y": 223
            },
            "rotated": false,
            "sourceSize": {
                "h": 32,
                "w": 32
            },
            "spriteSourceSize": {
                "h": 10,
                "w": 10,
                "x": 12,
                "y": 14
            },
            "trimmed": true
        },
        "mini_fatal_white.png": {
            "frame": {
                "h": 10,
                "w": 10,
                "x": 54,
                "y": 212
            },
            "rotated": false,
            "sourceSize": {
                "h": 32,
                "w": 32
            },
            "spriteSourceSize": {
                "h": 10,
                "w": 10,
                "x": 12,
                "y": 14
            },
            "trimmed": true
        },
        "mini_idle.png": {
            "frame": {
                "h": 12,
                "w": 10,
                "x": 66,
                "y": 158
            },
            "rotated": false,
            "sourceSize": {
                "h": 32,
                "w": 32
            },
            "spriteSourceSize": {
                "h": 12,
                "w": 10,
                "x": 12,
                "y": 12
            },
            "trimmed": true
        },
        "mini_idle_white.png": {
            "frame": {
                "h": 12,
                "w": 10,
                "x": 66,
                "y": 145
            },
            "rotated": false,
            "sourceSize": {
                "h": 32,
                "w": 32
            },
            "spriteSourceSize": {
                "h": 12,
                "w": 10,
                "x": 12,
                "y": 12
            },
            "trimmed": true
        },
        "mini_paralysis.png": {
            "frame": {
                "h": 11,
                "w": 12,
                "x": 67,
                "y": 87
            },
            "rotated": false,
            "sourceSize": {
                "h": 32,
                "w": 32
            },
            "spriteSourceSize": {
                "h": 11,
                "w": 12,
                "x": 11,
                "y": 13
            },
            "trimmed": true
        },
        "mini_ready.png": {
            "frame": {
                "h": 12,
                "w": 11,
                "x": 64,
                "y": 186
            },
            "rotated": false,
            "sourceSize": {
                "h": 32,
                "w": 32
            },
            "spriteSourceSize": {
                "h": 12,
                "w": 11,
                "x": 12,
                "y": 12
            },
            "trimmed": true
        },
        "mini_walk.png": {
            "frame": {
                "h": 12,
                "w": 11,
                "x": 64,
                "y": 173
            },
            "rotated": false,
            "sourceSize": {
                "h": 32,
                "w": 32
            },
            "spriteSourceSize": {
                "h": 12,
                "w": 11,
                "x": 11,
                "y": 12
            },
            "trimmed": true
        },
        "sleep.png": {
            "frame": {
                "h": 20,
                "w": 16,
                "x": 72,
                "y": 1
            },
            "rotated": false,
            "sourceSize": {
                "h": 32,
                "w": 32
            },
            "spriteSourceSize": {
                "h": 20,
                "w": 16,
                "x": 9,
                "y": 8
            },
            "trimmed": true
        },
        "sleep_white.png": {
            "frame": {
                "h": 20,
                "w": 16,
                "x": 53,
                "y": 22
            },
            "rotated": false,
            "sourceSize": {
                "h": 32,
                "w": 32
            },
            "spriteSourceSize": {
                "h": 20,
                "w": 16,
                "x": 9,
                "y": 8
            },
            "trimmed": true
        },
        "stone.png": {
            "frame": {
                "h": 24,
                "w": 15,
                "x": 18,
                "y": 126
            },
            "rotated": false,
            "sourceSize": {
                "h": 32,
                "w": 32
            },
            "spriteSourceSize": {
                "h": 24,
                "w": 15,
                "x": 9,
                "y": 4
            },
            "trimmed": true
        },
        "stone_white.png": {
            "frame": {
                "h": 24,
                "w": 15,
                "x": 18,
                "y": 76
            },
            "rotated": false,
            "sourceSize": {
                "h": 32,
                "w": 32
            },
            "spriteSourceSize": {
                "h": 24,
                "w": 15,
                "x": 9,
                "y": 4
            },
            "trimmed": true
        }
    },
    "meta": {
        "app": "ImagePacker",
        "format": "RGBA8888",
        "image": "img_chara.png",
        "size": {
            "h": 256,
            "w": 256
        },
        "version": "20140811"
    }
}